shennongname/__init__.py
shennongname/flask/blueprint/__init__.py
shennongname/flask/blueprint/snn.py
shennongname/flask/config.py
shennongname/flask/run.py
shennongname/lang/__init__.py
shennongname/lang/lang.py
shennongname/lang/locale/zh/LC_MESSAGES/messages.mo
shennongname/lang/locale/zh/LC_MESSAGES/messages.po
shennongname/snnmma/__init__.py
shennongname/snnmma/algorithm.py
shennongname/snnmma/model.py
shennongname/utils/__init__.py
shennongname/utils/sp2000_china.py
shennongname-1.1.0.dist-info/LICENSE
shennongname-1.1.0.dist-info/METADATA
shennongname-1.1.0.dist-info/WHEEL
shennongname-1.1.0.dist-info/RECORD
