Metadata-Version: 2.1
Name: shennongname
Version: 1.1.0
Summary: ShennongName (神农命名)
Author: YANG Zijie
Author-email: yangzijie@westlake.edu.cn
Requires-Python: >=3.11,<4.0
Classifier: Programming Language :: Python :: 3
Classifier: Programming Language :: Python :: 3.11
Classifier: Programming Language :: Python :: 3.12
Requires-Dist: flask (>=3.0.0,<4.0.0)
Requires-Dist: gunicorn (>=21.2.0,<22.0.0)
Requires-Dist: pandas (>=2.1.1,<3.0.0)
Requires-Dist: pydantic (>=2.4.2,<3.0.0)
Requires-Dist: pypinyin (>=0.49.0,<0.50.0)
Requires-Dist: python-dotenv (>=1.0.0,<2.0.0)
